{
    "comment_id": "6296286353811930",
    "comment_image": "https://scontent.fdac110-1.fna.fbcdn.net/v/t39.30808-6/339271237_894912821737026_1529636353576288866_n.jpg?stp=cp0_dst-jpg_e15_p235x165_q65&_nc_cat=110&ccb=1-7&_nc_sid=1480c5&efg=eyJpIjoidCJ9&_nc_eui2=AeEXxThdQSlrEYfFrLoLwDxkBWbwt6kWyU8FZvC3qRbJT-otan16b8gSpbBDubh70e8&_nc_ohc=uZDOqRhasskAX90Jva_&_nc_ht=scontent.fdac110-1.fna&oh=00_AfBJP6C3JKRnFskOYU5himNj9VmjOeA49OHDzUa8VoPQiA&oe=6430BB85",
    "comment_reaction_count": null,
    "comment_reactions": null,
    "comment_reactors": [],
    "comment_text": "Shamir Shahriar",
    "comment_time": "2023-04-03 09:00:00",
    "comment_url": "https://facebook.com/6296286353811930",
    "commenter_id": "647523672",
    "commenter_meta": null,
    "commenter_name": "Shamir Shahriar",
    "commenter_url": "https://facebook.com/TurnsyouintoCirque?groupid=537554109685212&eav=AfYhWY0OR6OSRkcFtyemPHRPuCIUMvcLQ72RPxcOcSGAjPM54__UtJW2X7dl170gAEc&refid=18&__tn__=R&paipv=0",
    "replies": [
        {
            "comment_id": "6296618283778737",
            "comment_image": null,
            "comment_reaction_count": null,
            "comment_reactions": null,
            "comment_reactors": [],
            "comment_text": "Shamir Shahriar \ud83e\udd23\ud83e\udd23",
            "comment_time": "2023-04-03 12:00:00",
            "comment_url": "https://facebook.com/6296618283778737",
            "commenter_id": "100023557703208",
            "commenter_meta": null,
            "commenter_name": "Abraham Evan",
            "commenter_url": "https://facebook.com/abraham.evan100?groupid=537554109685212&eav=AfaLAKvZ4WYrjUy4m4OAQe5aWCEwV6rzHCMvsXXmwuRN_nemHkoj9xFVhgQ1mhZP7Ls&__tn__=R&paipv=0"
        },
        {
            "comment_id": "6296841797089719",
            "comment_image": null,
            "comment_reaction_count": null,
            "comment_reactions": null,
            "comment_reactors": [],
            "comment_text": "Shahriar Abdullah jaba ghau ghau khachi khaba ?",
            "comment_time": "2023-04-03 14:00:00",
            "comment_url": "https://facebook.com/6296841797089719",
            "commenter_id": "647523672",
            "commenter_meta": null,
            "commenter_name": "Shamir Shahriar",
            "commenter_url": "https://facebook.com/TurnsyouintoCirque?groupid=537554109685212&eav=AfaSRm91mxv87s6TvL5dufkCQp7NmmPxFAyDShwV--QWp7e9za887xtpla25JY2jt0U&__tn__=R&paipv=0"
        },
        {
            "comment_id": "6296932360413996",
            "comment_image": null,
            "comment_reaction_count": null,
            "comment_reactions": null,
            "comment_reactors": [],
            "comment_text": "Shamir Shahriar yes, cholo ajkei jabo \ud83d\ude0e",
            "comment_time": "2023-04-03 14:00:00",
            "comment_url": "https://facebook.com/6296932360413996",
            "commenter_id": "100012151090924",
            "commenter_meta": null,
            "commenter_name": "Shahriar Abdullah",
            "commenter_url": "https://facebook.com/profile.php?id=100012151090924&groupid=537554109685212&eav=AfaWC4dIGRp00Xn57GCso2UxuSBvadThlHeDqWYO6M4DFj0vx0OoDW5KB7E4GkInAvo&__tn__=R&paipv=0"
        },
        {
            "comment_id": "6296947830412449",
            "comment_image": null,
            "comment_reaction_count": null,
            "comment_reactions": null,
            "comment_reactors": [],
            "comment_text": "Shahriar Abdullah amader bashai shamner doggo ta niye asho Jao , baire jaowar ki dorkar? \ud83d\udc38\ud83d\udc38",
            "comment_time": "2023-04-03 14:00:00",
            "comment_url": "https://facebook.com/6296947830412449",
            "commenter_id": "647523672",
            "commenter_meta": null,
            "commenter_name": "Shamir Shahriar",
            "commenter_url": "https://facebook.com/TurnsyouintoCirque?groupid=537554109685212&eav=AfZodppn2DkaD9Xih6uK3sfrmcaBB9D0ceHgyWBtz17fi2p8oIDMEosfDb-gBJ4Oe9U&__tn__=R&paipv=0"
        },
        {
            "comment_id": "6296958227078076",
            "comment_image": "https://scontent.fdac110-1.fna.fbcdn.net/m1/v/t6/An_F9bJG7govfshSMBkvcRLcxT0jmiXVYKtr7lgH5AHgUrjjpZ1OD0xyxXYgf7arc0lWgCdrR_KN4Mg7RSN3Gm3W6Gg03N1tQ-ZXzVvFJ_KvvB4.png?_nc_eui2=AeHsggsNjNxnl26yCLgCbzKNKRfFMSIc84YpF8UxIhzzhkOOTGJCWNnKoViaNdp9iqU&ccb=10-5&oh=00_AfBPyuf01Gpi5zgclcfAbFI6eYCrfOwdKTSsETm7tM4Iiw&oe=6452CAE7&_nc_sid=55e238",
            "comment_reaction_count": null,
            "comment_reactions": null,
            "comment_reactors": [],
            "comment_text": "Shamir Shahriar goto kal pa chatsilo amr, ore bolle ekhoni oy shohid hoya readymade ranna hoya ashbe, context bujhe gesi thanks ar lagbe na\ud83c\udf1a",
            "comment_time": "2023-04-03 15:00:00",
            "comment_url": "https://facebook.com/6296958227078076",
            "commenter_id": "100012151090924",
            "commenter_meta": null,
            "commenter_name": "Shahriar Abdullah",
            "commenter_url": "https://facebook.com/profile.php?id=100012151090924&groupid=537554109685212&eav=Afb3zI6_Mb92HlkRHurQFfNFXAqIMbMc-LY_CsjM5aJ5uG1zkyWwQm7lCxutRRh4qh0&__tn__=R&paipv=0"
        }
    ]
}