{
    "comment_id": "6296952700411962",
    "comment_image": null,
    "comment_reaction_count": null,
    "comment_reactions": null,
    "comment_reactors": [],
    "comment_text": "Keya Showrav Hira ki bolse",
    "comment_time": "2023-04-03 14:00:00",
    "comment_url": "https://facebook.com/6296952700411962",
    "commenter_id": "100006454437775",
    "commenter_meta": null,
    "commenter_name": "Ishtiaque Taniya Masum",
    "commenter_url": "https://facebook.com/istiyak.masum.9?groupid=537554109685212&eav=AfbysQwayWaqYiQ61LisxsEr-BALeUj1nd8I7PJ0QQoOk7q7otl6gnVLW6IDOj-ElWI&refid=18&__tn__=R&paipv=0",
    "replies": [
        {
            "comment_id": "6297075700399662",
            "comment_image": null,
            "comment_reaction_count": null,
            "comment_reactions": null,
            "comment_reactors": [],
            "comment_text": "Ishtiaque Taniya Masum 3 jon er bil dile ek jon free khaite parbe...",
            "comment_time": "2023-04-03 15:00:00",
            "comment_url": "https://facebook.com/6297075700399662",
            "commenter_id": "100034798968228",
            "commenter_meta": null,
            "commenter_name": "Keya Showrav Hira",
            "commenter_url": "https://facebook.com/saifan.hk.9?groupid=537554109685212&eav=AfaLJ9OKyH6HwPXnd_6t3rAt0gN30tztZBkcnR8V6OkYgVSYQcL9cGTkEiulalhddLk&__tn__=R&paipv=0"
        },
        {
            "comment_id": "6297080480399184",
            "comment_image": null,
            "comment_reaction_count": null,
            "comment_reactions": null,
            "comment_reactors": [],
            "comment_text": "Keya Showrav Hira chol jai",
            "comment_time": "2023-04-03 15:00:00",
            "comment_url": "https://facebook.com/6297080480399184",
            "commenter_id": "100006454437775",
            "commenter_meta": null,
            "commenter_name": "Ishtiaque Taniya Masum",
            "commenter_url": "https://facebook.com/istiyak.masum.9?groupid=537554109685212&eav=Afa_vHmDlIvfWt_efSRw-T7waDAIJaRvAuVgH1qEiE5-ju7zhF8gPpb-i8DTrBhykvk&__tn__=R&paipv=0"
        },
        {
            "comment_id": "6297080877065811",
            "comment_image": null,
            "comment_reaction_count": null,
            "comment_reactions": null,
            "comment_reactors": [],
            "comment_text": "Keya Showrav Hira tui Ami r hira",
            "comment_time": "2023-04-03 15:00:00",
            "comment_url": "https://facebook.com/6297080877065811",
            "commenter_id": "100006454437775",
            "commenter_meta": null,
            "commenter_name": "Ishtiaque Taniya Masum",
            "commenter_url": "https://facebook.com/istiyak.masum.9?groupid=537554109685212&eav=AfZU6EE4sIubIRlCuhM5fri_GEsLucc7URk-v8WQRYBrn4itYVA31qiSuKY9kHu9sZc&__tn__=R&paipv=0"
        }
    ]
}