{
    "comment_id": "6297490480358184",
    "comment_image": null,
    "comment_reaction_count": null,
    "comment_reactions": null,
    "comment_reactors": [],
    "comment_text": "\u0985\u09a6\u09cd\u09b0\u09bf\u09a4\u09be \u0990\u09b6\u09c0",
    "comment_time": "2023-04-03 18:00:00",
    "comment_url": "https://facebook.com/6297490480358184",
    "commenter_id": "100083939508351",
    "commenter_meta": null,
    "commenter_name": "Joba Jui",
    "commenter_url": "https://facebook.com/profile.php?id=100083939508351&groupid=537554109685212&eav=AfaKEy75pwfBvnFo0mfIEXO5kF2FsAWpiNU_mm9EUNLZ-4G4V67tbsUubRns9D2r_eA&refid=18&__tn__=R&paipv=0",
    "replies": []
}