{
    "comment_id": "6297446803695885",
    "comment_image": null,
    "comment_reaction_count": null,
    "comment_reactions": null,
    "comment_reactors": [],
    "comment_text": "Ismail Fahad ja guira ay",
    "comment_time": "2023-04-03 18:00:00",
    "comment_url": "https://facebook.com/6297446803695885",
    "commenter_id": "100010375027786",
    "commenter_meta": null,
    "commenter_name": "Rihan Ahmed",
    "commenter_url": "https://facebook.com/profile.php?id=100010375027786&groupid=537554109685212&eav=AfZoV4x9ImU8jpaO1PloQJxqxqALV3iqNauZaM-yeksKfKbjjV4Sl1CSQPAMHZQfWXo&refid=18&__tn__=R&paipv=0",
    "replies": []
}