{
    "comment_id": "6297788766995022",
    "comment_image": null,
    "comment_reaction_count": null,
    "comment_reactions": null,
    "comment_reactors": [],
    "comment_text": "Aida ki Justin bd version?",
    "comment_time": "2023-04-03 20:00:00",
    "comment_url": "https://facebook.com/6297788766995022",
    "commenter_id": "100016846416419",
    "commenter_meta": null,
    "commenter_name": "Shahriar Islam Imon",
    "commenter_url": "https://facebook.com/shahriarislam.imon.5?groupid=537554109685212&eav=AfZpssSu8OLg_F4Cq2ryhNZS92jxknfF44LruR_LnndBx1lll8YBgBZSxgWF3ABKBCw&refid=18&__tn__=%7ER&paipv=0",
    "replies": []
}