{
    "comment_id": "6297595103681055",
    "comment_image": null,
    "comment_reaction_count": null,
    "comment_reactions": null,
    "comment_reactors": [],
    "comment_text": "\u0633\u0644\u0645 \u0627\u0643\u062a\u0631 \u0634\u0641\u0627",
    "comment_time": "2023-04-03 19:00:00",
    "comment_url": "https://facebook.com/6297595103681055",
    "commenter_id": "100090141922062",
    "commenter_meta": null,
    "commenter_name": "Md Osman",
    "commenter_url": "https://facebook.com/profile.php?id=100090141922062&groupid=537554109685212&eav=AfbvF2cRyAYaT5Z8rGpzQ7KCtYwNql6QaRokSGELrx7ShqiXJzBsHzma6UcIMRL0y7E&refid=18&__tn__=R&paipv=0",
    "replies": []
}