{
    "comment_id": "6297704913670074",
    "comment_image": null,
    "comment_reaction_count": null,
    "comment_reactions": null,
    "comment_reactors": [],
    "comment_text": "Ridhi Kabir",
    "comment_time": "2023-04-03 19:00:00",
    "comment_url": "https://facebook.com/6297704913670074",
    "commenter_id": "100091275971449",
    "commenter_meta": null,
    "commenter_name": "Akibul Islam",
    "commenter_url": "https://facebook.com/profile.php?id=100091275971449&groupid=537554109685212&eav=AfZ78aG4C8p1YNdOGGn2Efy-j38ecMT3-Be7QxlsJTlvL-AM2GouiMnbpMGk0RR4pRk&refid=18&__tn__=R&paipv=0",
    "replies": []
}