{
    "comment_id": "6298229533617612",
    "comment_image": null,
    "comment_reaction_count": null,
    "comment_reactions": null,
    "comment_reactors": [],
    "comment_text": "Wow www wow",
    "comment_time": "2023-04-03 23:05:00",
    "comment_url": "https://facebook.com/6298229533617612",
    "commenter_id": "100069797890704",
    "commenter_meta": null,
    "commenter_name": "Kazi Tasnim",
    "commenter_url": "https://facebook.com/profile.php?id=100069797890704&groupid=537554109685212&eav=AfZDEYOszD2bWy4IwbGNHzQUt_J2JqzbN5P8cXIjdnPiacsqtf8qNvBI-eX0o2spzKc&refid=18&__tn__=R&paipv=0",
    "replies": []
}