{
    "comment_id": "6298085230298709",
    "comment_image": null,
    "comment_reaction_count": null,
    "comment_reactions": null,
    "comment_reactors": [],
    "comment_text": "\ud83d\udc9d\ud83d\udc9d",
    "comment_time": "2023-04-03 22:00:00",
    "comment_url": "https://facebook.com/6298085230298709",
    "commenter_id": "100015322598922",
    "commenter_meta": null,
    "commenter_name": "\u09b0\u09cb\u09a6\u09c7\u09b2\u09be \u09a6\u09c2\u09aa\u09c1\u09b0",
    "commenter_url": "https://facebook.com/hrhori.roy.7?groupid=537554109685212&eav=AfZrEt5pzGwENastVIhiGb7XOWOk1NQ3V8aW2gFlmOma_lXSCvPA8teo0j3WwsefFO0&refid=18&__tn__=R&paipv=0",
    "replies": []
}