{
    "comment_id": "6296620850445147",
    "comment_image": null,
    "comment_reaction_count": null,
    "comment_reactions": null,
    "comment_reactors": [],
    "comment_text": "Azhar Mahmud Emon Poster Milon is Everywhere \ud83d\ude06",
    "comment_time": "2023-04-03 12:00:00",
    "comment_url": "https://facebook.com/6296620850445147",
    "commenter_id": "100023557703208",
    "commenter_meta": null,
    "commenter_name": "Abraham Evan",
    "commenter_url": "https://facebook.com/abraham.evan100?groupid=537554109685212&eav=Afb6obt8k2SFOMHBhKI39n3K1GHkPWmPlEBcjnVNiN8WwQelWhHOEIDxMecqLhRCy80&__tn__=R&paipv=0"
}