{
    "comment_id": "6297676790339553",
    "comment_image": null,
    "comment_reaction_count": null,
    "comment_reactions": null,
    "comment_reactors": [],
    "comment_text": "Kausar Ahmed any Friday",
    "comment_time": "2023-04-03 20:00:00",
    "comment_url": "https://facebook.com/6297676790339553",
    "commenter_id": "100046705505616",
    "commenter_meta": null,
    "commenter_name": "Onio Paul Pintu",
    "commenter_url": "https://facebook.com/profile.php?id=100046705505616&groupid=537554109685212&eav=AfZkk4ADGuBywBXdTM4-jOl4v2_xno8Y3lXaNSxQrg0dLUaHJE9VJpus60erqIvXHao&__tn__=R&paipv=0"
}